MANIFEST.in
README.rst
setup.py
django_sphinx.egg-info/PKG-INFO
django_sphinx.egg-info/SOURCES.txt
django_sphinx.egg-info/dependency_links.txt
django_sphinx.egg-info/requires.txt
django_sphinx.egg-info/top_level.txt
djangosphinx/__init__.py
djangosphinx/admin.py
djangosphinx/config.py
djangosphinx/constants.py
djangosphinx/manager.py
djangosphinx/models.py
djangosphinx/apis/__init__.py
djangosphinx/apis/current.py
djangosphinx/apis/api263/__init__.py
djangosphinx/apis/api275/__init__.py
djangosphinx/apis/api278/__init__.py
djangosphinx/management/__init__.py
djangosphinx/management/commands/__init__.py
djangosphinx/management/commands/generate_sphinx_config.py
djangosphinx/templates/index-multiple.conf
djangosphinx/templates/index.conf
djangosphinx/templates/source-multiple.conf
djangosphinx/templates/source.conf
djangosphinx/templates/sphinx.conf
djangosphinx/utils/__init__.py
djangosphinx/utils/config.py
sphinxtest/__init__.py
sphinxtest/manage.py
sphinxtest/settings.py
sphinxtest/urls.py
sphinxtest/tests/__init__.py
sphinxtest/tests/models.py
sphinxtest/tests/views.py