Metadata-Version: 1.0
Name: django-sphinx
Version: 2.2.4
Summary: An integration layer bringing Django and Sphinx Search together.
Home-page: http://github.com/dcramer/django-sphinx
Author: David Cramer
Author-email: dcramer@gmail.com
License: UNKNOWN
Platform: UNKNOWN
Classifier: Framework :: Django
Classifier: Intended Audience :: Developers
Classifier: Intended Audience :: System Administrators
Classifier: Operating System :: OS Independent
Classifier: Topic :: Software Development
